README.rst
setup.py
python_travis_docker_test/__init__.py
python_travis_docker_test/fibonacci.py
travis_docker_python.egg-info/PKG-INFO
travis_docker_python.egg-info/SOURCES.txt
travis_docker_python.egg-info/dependency_links.txt
travis_docker_python.egg-info/top_level.txt