Metadata-Version: 1.1
Name: travis-docker-python
Version: 0.0.1
Summary: A sample Python project to demo travisCI Docker python ansible postgresql
Home-page: https://github.com/Shashankreddysunkara/travis-docker-python
Author: Shashank Reddy Sunkara
Author-email: shashank@datacultr.com
License: MIT
Keywords: python travisCI Docker ansible postgresql
Platform: UNKNOWN
Classifier: Development Status :: 3 - Alpha
Classifier: Intended Audience :: Developers
Classifier: Topic :: Software Development :: Build Tools
Classifier: License :: OSI Approved :: MIT License
Classifier: Programming Language :: Python :: 2
Classifier: Programming Language :: Python :: 2.6
Classifier: Programming Language :: Python :: 2.7
Classifier: Programming Language :: Python :: 3
Classifier: Programming Language :: Python :: 3.3
Classifier: Programming Language :: Python :: 3.4
Classifier: Programming Language :: Python :: 3.6
